base_account
base_media
base_page
form
monomail
sharing
site_admin
tracking
