Metadata-Version: 1.1
Name: cgp-django-core
Version: 0.20
Summary: Core CGP Django Libraries
Home-page: https://bitbucket.org/cgpartners/cgp-django-core
Author: Nina Pavlich
Author-email: nina@cgparntersllc.com
License: UNKNOWN
Keywords: libraries,web development
Platform: UNKNOWN
Classifier: Development Status :: 5 - Production/Stable
Classifier: Environment :: Web Environment
Classifier: Framework :: Django
Classifier: Intended Audience :: Developers
Classifier: License :: OSI Approved
Classifier: Operating System :: OS Independent
Classifier: Programming Language :: Python
